tensorstore-stubs/__init__.pyi
tensorstore-stubs/_tensorstore.pyi
tensorstore-stubs/py.typed
tensorstore_stubs-0.1.2.dist-info/LICENSE
tensorstore_stubs-0.1.2.dist-info/METADATA
tensorstore_stubs-0.1.2.dist-info/WHEEL
tensorstore_stubs-0.1.2.dist-info/top_level.txt
tensorstore_stubs-0.1.2.dist-info/RECORD
