Metadata-Version: 2.1
Name: tensorstore-stubs
Version: 0.1.2
Summary: Type stubs for tensorstore
Author-email: elda27 <kaz.birdstick@gmail.com>
License: Apache 2.0
Requires-Python: >=3.8
License-File: LICENSE
Requires-Dist: tensorstore >=0.1.45
